Sources/pruebaNormalizacion.v
//q1: realimentacion de mantisa
//q2: realimentacion de exponente
//q3: salida de mantisa definitiva ya normalizada
//q4: salida de exponente definitiva ya normalizada
module normalizacion # ( parameter SIZE=10 ) (clkNorm, vect,exp,enable,q1,q2,q3,q4);
   //INPUTS NO PUEDEN SER REGISTROS
   //% This module is for preparing the data to be computed by additions, substractions, multiplications and divisions.
   //% This is a non-RTL module, but eventually it can be coded in RTL mode.
   input [SIZE-1:0] vect;
   input [4:0] exp;
   output reg [SIZE-1:0] q1,q3;
   output  reg [4:0] q2,q4;
   
   input clkNorm, enable;
   
   always @ (negedge clkNorm ) begin
	   if(enable) begin
			if(vect[SIZE-1]==0) begin
				q1 = (vect << 1);			//roto la mantisa a la izquierda
				q2=exp-1;
			end
			else begin
				q3 = (vect >> 1);			//roto la mantisa a la derecha y lo guardo en q3 que tiene el valor de la mantisa def.
				q4 = exp + 1'b1; 
			end
	   end
	end
endmodule

Sources/mux2.v
module mux2 # ( parameter SIZE=10 ) (a1,sel0,sel1,q0);
//% This module is a common 2 input multiplexor. 
//% Note the this is writen in non-RTL description but it can eventually be passed to RTL description.
	input a1;
	input signed [SIZE-1:0] sel0,sel1;
    output reg [SIZE-1:0] q0 ;
    
    
    always @(a1 or sel0 or sel1)  //Condicion de funcionamiento de un mux 2:1
    begin
		if(a1)
		 q0<= sel1;
		else
		 q0<= sel0;
	end
	
endmodule

Sources/Normalize.v
module Normalize # ( parameter SIZE=10 ) (Clock,clkNorm,iVect,iExp,oMant,oExp);
//% This module is the following step to the normalization phase.
	input Clock,clkNorm;
    input [SIZE-1:0] iVect;
    input [4:0] iExp;
    output [SIZE-1:0] oMant;
    output [4:0] oExp;
	
	wire [SIZE-1:0] reMantReal0, mantisaReal0;
	wire [4:0] reExpReal0, expReal0;
	//Fase de muxes parte Real
	mux2 #(SIZE) muxMantReal0(Clock,reMantReal0,iVect,mantisaReal0);
	mux2 #(5) muxExpoReal0(Clock,reExpReal0,iExp,expReal0);
	
	//fase de normalizacion parte Real
	normalizacion #(SIZE) normReal0 (clkNorm,mantisaReal0,expReal0,~Clock,reMantReal0,reExpReal0,oMant,oExp);
	

endmodule

Sources/float_multiplier.v
module float_multiplier
//% This module is a float multiplier calculator. It recieves two clocks, two operands by mantisa and exponent part and computes the producs.
	(
	input clkExt,
	input clkNorm,
	input signed [9:0] iMant1,//Mantisas de entrada son de 10 bits y los exponentes de 5 bits
	input signed [4:0] iExp1,
	input signed [9:0] iMant2,
	input signed [4:0] iExp2,
	output [14:0] oMantR,
	output [4:0] oExpR
	);
	
	wire signed [18:0] MantisaPre;
	wire signed [4:0] ExpPre;
		
	wire signed [18:0]q1, q3;
	wire signed [4:0]q2, q4;
	
	//Operación de la multiplicación
	assign MantisaPre = iMant1*iMant2;
	assign ExpPre = iExp1 + iExp2;
	
	
	//Conexión del renormalizador
	Normalize #19 reNormalize (clkExt,clkNorm,MantisaPre,ExpPre,q3,q4);
	
	assign oMantR = q3[18:4];
	assign oExpR = q4;

endmodule

Sources/float_multiplier_testbench.v
`include "float_multiplier.v"
`include "Normalize.v"
`include "pruebaNormalizacion.v"
`include "mux2.v"


module tester();
//% This module is for testing the float_multiplier module with some samples. 
//% By the way I hardly recommend to do not change the name of this module, even if it is confused and problematic.
	reg clkExt, clkNorm;
	reg [9:0] iMant1, iMant2;
	reg [4:0] iExp1, iExp2;
	wire [14:0] oMantR;
	wire [4:0] oExpR;
	
	float_multiplier mult1(clkExt, clkNorm, iMant1, iExp1, iMant2, iExp2, oMantR, oExpR);
	
	initial begin
		clkExt = 0;
		clkNorm = 0;
		iExp1 = 5'b11101;
		iExp2 = 5'b00011;
		iMant1 = 10'b0111011100;
		iMant2 = 10'b0100010000;
	end 
	
	always begin
				#1 clkNorm = ~clkNorm;
			end
	
	always begin
				#20 clkExt = ~clkExt;
			end
	
	always begin
				#40 iMant1 = iMant1 + 3;
					iMant2 = iMant2 + 1;
			end
	
	initial #200 $finish;
	
	initial
		begin
			$monitor($time, "  iExp1 = %b, iMant1 = %b, iExp2 = %b, iMant2 = %b, Resultado: %b x2 %b", iExp1, iMant1, iExp2, iMant2, oMantR, oExpR );
			$dumpfile("float_multiplier_testbench.vcd");
			$dumpvars;
		end
	


endmodule

Sources/float_multiplier_testbench.vcd
$date
	Wed Dec 17 10:36:21 2014
$end
$version
	Icarus Verilog
$end
$timescale
	1s
$end
$scope module tester $end
$var wire 15 ! oMantR [14:0] $end
$var wire 5 " oExpR [4:0] $end
$var reg 1 # clkExt $end
$var reg 1 $ clkNorm $end
$var reg 5 % iExp1 [4:0] $end
$var reg 5 & iExp2 [4:0] $end
$var reg 10 ' iMant1 [9:0] $end
$var reg 10 ( iMant2 [9:0] $end
$scope module mult1 $end
$var wire 1 # clkExt $end
$var wire 1 $ clkNorm $end
$var wire 5 ) iExp1 [4:0] $end
$var wire 5 * iExp2 [4:0] $end
$var wire 10 + iMant1 [9:0] $end
$var wire 10 , iMant2 [9:0] $end
$var wire 5 - oExpR [4:0] $end
$var wire 5 . q4 [4:0] $end
$var wire 19 / q3 [18:0] $end
$var wire 15 0 oMantR [14:0] $end
$var wire 19 1 MantisaPre [18:0] $end
$var wire 5 2 ExpPre [4:0] $end
$scope module reNormalize $end
$var wire 1 # Clock $end
$var wire 1 $ clkNorm $end
$var wire 5 3 iExp [4:0] $end
$var wire 19 4 iVect [18:0] $end
$var wire 19 5 reMantReal0 [18:0] $end
$var wire 5 6 reExpReal0 [4:0] $end
$var wire 19 7 oMant [18:0] $end
$var wire 5 8 oExp [4:0] $end
$var wire 19 9 mantisaReal0 [18:0] $end
$var wire 5 : expReal0 [4:0] $end
$scope module muxExpoReal0 $end
$var wire 1 # a1 $end
$var wire 5 ; sel1 [4:0] $end
$var wire 5 < sel0 [4:0] $end
$var reg 5 = q0 [4:0] $end
$upscope $end
$scope module muxMantReal0 $end
$var wire 1 # a1 $end
$var wire 19 > sel1 [18:0] $end
$var wire 19 ? sel0 [18:0] $end
$var reg 19 @ q0 [18:0] $end
$upscope $end
$scope module normReal0 $end
$var wire 1 $ clkNorm $end
$var wire 1 A enable $end
$var wire 5 B exp [4:0] $end
$var wire 19 C vect [18:0] $end
$var reg 19 D q1 [18:0] $end
$var reg 5 E q2 [4:0] $end
$var reg 19 F q3 [18:0] $end
$var reg 5 G q4 [4:0] $end
$upscope $end
$upscope $end
$upscope $end
$upscope $end
$enddefinitions $end
#0
$dumpvars
bx G
b0xxxxxxxxxxxxxxxxxx F
bx E
bx D
bx C
bx B
1A
bx @
bx ?
b11111100111000000 >
bx =
bx <
b0 ;
bx :
bx 9
bx 8
b0xxxxxxxxxxxxxxxxxx 7
bx 6
bx 5
b11111100111000000 4
b0 3
b0 2
b11111100111000000 1
b0xxxxxxxxxxxxxx 0
b0xxxxxxxxxxxxxxxxxx /
bx .
bx -
b100010000 ,
b111011100 +
b11 *
b11101 )
b100010000 (
b111011100 '
b11 &
b11101 %
0$
0#
bx "
b0xxxxxxxxxxxxxx !
$end
#1
1$
#2
0$
#3
1$
#4
0$
#5
1$
#6
0$
#7
1$
#8
0$
#9
1$
#10
0$
#11
1$
#12
0$
#13
1$
#14
0$
#15
1$
#16
0$
#17
1$
#18
0$
#19
1$
#20
b0 :
b0 =
b0 B
b11111100111000000 9
b11111100111000000 @
b11111100111000000 C
0A
0$
1#
#21
1$
#22
0$
#23
1$
#24
0$
#25
1$
#26
0$
#27
1$
#28
0$
#29
1$
#30
0$
#31
1$
#32
0$
#33
1$
#34
0$
#35
1$
#36
0$
#37
1$
#38
0$
#39
1$
#40
b11111 :
b11111 =
b11111 B
b111111001110000000 9
b111111001110000000 @
b111111001110000000 C
b11111 6
b11111 <
b11111 E
b111111001110000000 5
b111111001110000000 ?
b111111001110000000 D
1A
0$
0#
b100010001 (
b100010001 ,
b11111111011001111 1
b11111111011001111 4
b11111111011001111 >
b111011111 '
b111011111 +
#41
1$
#42
b11110 :
b11110 =
b11110 B
b1111110011100000000 9
b1111110011100000000 @
b1111110011100000000 C
b11110 6
b11110 <
b11110 E
b1111110011100000000 5
b1111110011100000000 ?
b1111110011100000000 D
0$
#43
1$
#44
b11111100111000 !
b11111100111000 0
b11111 "
b11111 -
b11111 .
b11111 8
b11111 G
b111111001110000000 /
b111111001110000000 7
b111111001110000000 F
0$
#45
1$
#46
0$
#47
1$
#48
0$
#49
1$
#50
0$
#51
1$
#52
0$
#53
1$
#54
0$
#55
1$
#56
0$
#57
1$
#58
0$
#59
1$
#60
b0 :
b0 =
b0 B
b11111111011001111 9
b11111111011001111 @
b11111111011001111 C
0A
0$
1#
#61
1$
#62
0$
#63
1$
#64
0$
#65
1$
#66
0$
#67
1$
#68
0$
#69
1$
#70
0$
#71
1$
#72
0$
#73
1$
#74
0$
#75
1$
#76
0$
#77
1$
#78
0$
#79
1$
#80
b11111 :
b11111 =
b11111 B
b111111110110011110 9
b111111110110011110 @
b111111110110011110 C
b11111 6
b11111 <
b11111 E
b111111110110011110 5
b111111110110011110 ?
b111111110110011110 D
1A
0$
0#
b100010010 (
b100010010 ,
b100000001111100100 1
b100000001111100100 4
b100000001111100100 >
b111100010 '
b111100010 +
#81
1$
#82
b11110 :
b11110 =
b11110 B
b1111111101100111100 9
b1111111101100111100 @
b1111111101100111100 C
b11110 6
b11110 <
b11110 E
b1111111101100111100 5
b1111111101100111100 ?
b1111111101100111100 D
0$
#83
1$
#84
b11111111011001 !
b11111111011001 0
b111111110110011110 /
b111111110110011110 7
b111111110110011110 F
0$
#85
1$
#86
0$
#87
1$
#88
0$
#89
1$
#90
0$
#91
1$
#92
0$
#93
1$
#94
0$
#95
1$
#96
0$
#97
1$
#98
0$
#99
1$
#100
b0 :
b0 =
b0 B
b100000001111100100 9
b100000001111100100 @
b100000001111100100 C
0A
0$
1#
#101
1$
#102
0$
#103
1$
#104
0$
#105
1$
#106
0$
#107
1$
#108
0$
#109
1$
#110
0$
#111
1$
#112
0$
#113
1$
#114
0$
#115
1$
#116
0$
#117
1$
#118
0$
#119
1$
#120
b11111 :
b11111 =
b11111 B
b1000000011111001000 9
b1000000011111001000 @
b1000000011111001000 C
b11111 6
b11111 <
b11111 E
b1000000011111001000 5
b1000000011111001000 ?
b1000000011111001000 D
1A
0$
0#
b100010011 (
b100010011 ,
b100000100011111111 1
b100000100011111111 4
b100000100011111111 >
b111100101 '
b111100101 +
#121
1$
#122
b10000000111110 !
b10000000111110 0
b0 "
b0 -
b0 .
b0 8
b0 G
b100000001111100100 /
b100000001111100100 7
b100000001111100100 F
0$
#123
1$
#124
0$
#125
1$
#126
0$
#127
1$
#128
0$
#129
1$
#130
0$
#131
1$
#132
0$
#133
1$
#134
0$
#135
1$
#136
0$
#137
1$
#138
0$
#139
1$
#140
b0 :
b0 =
b0 B
b100000100011111111 9
b100000100011111111 @
b100000100011111111 C
0A
0$
1#
#141
1$
#142
0$
#143
1$
#144
0$
#145
1$
#146
0$
#147
1$
#148
0$
#149
1$
#150
0$
#151
1$
#152
0$
#153
1$
#154
0$
#155
1$
#156
0$
#157
1$
#158
0$
#159
1$
#160
b11111 :
b11111 =
b11111 B
b1000001000111111110 9
b1000001000111111110 @
b1000001000111111110 C
b1000001000111111110 5
b1000001000111111110 ?
b1000001000111111110 D
1A
0$
0#
b100010100 (
b100010100 ,
b100000111000100000 1
b100000111000100000 4
b100000111000100000 >
b111101000 '
b111101000 +
#161
1$
#162
b10000010001111 !
b10000010001111 0
b100000100011111111 /
b100000100011111111 7
b100000100011111111 F
0$
#163
1$
#164
0$
#165
1$
#166
0$
#167
1$
#168
0$
#169
1$
#170
0$
#171
1$
#172
0$
#173
1$
#174
0$
#175
1$
#176
0$
#177
1$
#178
0$
#179
1$
#180
b0 :
b0 =
b0 B
b100000111000100000 9
b100000111000100000 @
b100000111000100000 C
0A
0$
1#
#181
1$
#182
0$
#183
1$
#184
0$
#185
1$
#186
0$
#187
1$
#188
0$
#189
1$
#190
0$
#191
1$
#192
0$
#193
1$
#194
0$
#195
1$
#196
0$
#197
1$
#198
0$
#199
1$
#200
b11111 :
b11111 =
b11111 B
b1000001110001000000 9
b1000001110001000000 @
b1000001110001000000 C
b1000001110001000000 5
b1000001110001000000 ?
b1000001110001000000 D
1A
0$
0#
b100010101 (
b100010101 ,
b100001001101000111 1
b100001001101000111 4
b100001001101000111 >
b111101011 '
b111101011 +
