Sources/sign_changer.v
module complement_data # (parameter SIZE=8) (a,sign,b);
//% This module passes from normal data (without been complemented previously) to complemented data
   input [SIZE-1:0] a;
   output [SIZE-1:0] b;
   output sign;
   
   assign b = (a[SIZE-1]) ? (~a+1'b1) :a;
   assign sign = a[SIZE-1];
	
endmodule

module descomplement_data # (parameter SIZE=8) (a,signAnt,b);
//% This module passes from complemented data non-complemented data
   input [SIZE-1:0] a;
   input signAnt;
   output [SIZE-1:0] b;
   
   //Si signAnt es uno quiere decir que era negativo y complementa
   assign b = (signAnt) ? (~a+1'b1) :a;
  
endmodule

Sources/pruebaNormalizacion.v
//q1: realimentacion de mantisa
//q2: realimentacion de exponente
//q3: salida de mantisa definitiva ya normalizada
//q4: salida de exponente definitiva ya normalizada
module normalizacion # ( parameter SIZE=10 ) (clkNorm, vect,exp,enable,q1,q2,q3,q4);
   //INPUTS NO PUEDEN SER REGISTROS
   //% This module is for preparing the data to be computed by additions, substractions, multiplications and divisions.
   //% This is a non-RTL module, but eventually it can be coded in RTL mode.
   input [SIZE-1:0] vect;
   input [4:0] exp;
   output reg [SIZE-1:0] q1,q3;
   output  reg [4:0] q2,q4;
   
   input clkNorm, enable;
   
   always @ (negedge clkNorm ) begin
	   if(enable) begin
			if(vect[SIZE-1]==0) begin
				q1 = (vect << 1);			//roto la mantisa a la izquierda
				q2=exp-1;
			end
			else begin
				q3 = (vect >> 1);			//roto la mantisa a la derecha y lo guardo en q3 que tiene el valor de la mantisa def.
				q4 = exp + 1'b1; 
			end
	   end
	end
endmodule

Sources/mux2.v
module mux2 # ( parameter SIZE=10 ) (a1,sel0,sel1,q0);
//% This module is a common 2 input multiplexor. 
//% Note the this is writen in non-RTL description but it can eventually be passed to RTL description.
	input a1;
	input signed [SIZE-1:0] sel0,sel1;
    output reg [SIZE-1:0] q0 ;
    
    
    always @(a1 or sel0 or sel1)  //Condicion de funcionamiento de un mux 2:1
    begin
		if(a1)
		 q0<= sel1;
		else
		 q0<= sel0;
	end
	
endmodule

Sources/Normalize.v
module Normalize # ( parameter SIZE=10 ) (Clock,clkNorm,iVect,iExp,oMant,oExp);
//% This module is the following step to the normalization phase.
	input Clock,clkNorm;
    input [SIZE-1:0] iVect;
    input [4:0] iExp;
    output [SIZE-1:0] oMant;
    output [4:0] oExp;
	
	wire [SIZE-1:0] reMantReal0, mantisaReal0;
	wire [4:0] reExpReal0, expReal0;
	//Fase de muxes parte Real
	mux2 #(SIZE) muxMantReal0(Clock,reMantReal0,iVect,mantisaReal0);
	mux2 #(5) muxExpoReal0(Clock,reExpReal0,iExp,expReal0);
	
	//fase de normalizacion parte Real
	normalizacion #(SIZE) normReal0 (clkNorm,mantisaReal0,expReal0,~Clock,reMantReal0,reExpReal0,oMant,oExp);
	

endmodule

Sources/float_adder.v
module float_adder(
	//%This module is a float adder, it recieves two inputs, two operands by mantisa and exponent part and it computes the addition.
	input clcExt,//Reloj lento
	input clkNorm,//Reloj interno, rapido
	input signed [14:0]  iMant1,//Mantisas de entrada son de 15 bits y los exponentes de 5 bits
	input signed [4:0] iExp1,
	input signed [14:0] iMant2,
	input signed [4:0] iExp2,
	output [14:0] oMantR,
	output [4:0] oExpR
	);
	
	reg [14:0] Mant3;
	
	reg [15:0] MantisaPre;
	wire [15:0] MantisaPre_cp;
	reg [4:0] ExpPre;
	

	//reg [10:0] MantisaMux;
	//reg [4:0] ExpMux;
	
	wire signed [15:0] q1, q3, q3_dcp;
	wire signed [4:0] q2, q4;
	
	always @(*) begin
	//Operación de la suma
		if(iExp1 > iExp2)
			begin
				Mant3 = iMant2 >> (iExp1 - iExp2);
				{MantisaPre[15],MantisaPre[14:0]} = Mant3 + iMant1;
				//assign MantisaPre = Mant3 + iMant1;
				ExpPre = iExp1;
			end
		else
			begin
				Mant3 = iMant1 >> (iExp2 - iExp1);
				//assign MantisaPre = Mant3 + iMant2;
				{MantisaPre[15],MantisaPre[14:0]} = Mant3 + iMant2;
				ExpPre = iExp2;
			end
	end
	
	//Conexión del renormalizador
	complement_data #16 complementData51(MantisaPre, Mantisa_sign, MantisaPre_cp);
	Normalize #(16) renormalize(clcExt,clkNorm,MantisaPre_cp,ExpPre,q3,q4);
	descomplement_data #16 descomp1(q3, Mantisa_sign, q3_dcp);
	
	assign oMantR = q3_dcp[15:1];
	assign oExpR = q4;

endmodule

Sources/float_adder_testbench.v
`include "float_adder.v"
`include "Normalize.v"
`include "pruebaNormalizacion.v"
`include "mux2.v"
`include "sign_changer.v"

//Test bench para el modulo float_adder.v
module float_adder_testbench; 
//%This module is for testing the float_adder module with some relevant samples.
	
	//inputs
	input [14:0] oMantR;
	input [4:0] oExpR;

	//outputs
	output reg signed [14:0] iMant1;
	output reg signed [4:0] iExp1;
	output reg signed [14:0] iMant2;
	output reg signed [4:0] iExp2;

	//clock
	reg clk;
	reg clcext;

	initial 
		begin
			#0 clk=0;
			clcext = 1;
		end
	always
		#40 clcext= ~clcext;
		
	always
		#1 clk=~clk;
		

	time simulationTime;

	//Instancia del modulo
	float_adder F1(clcext, clk, iMant1, iExp1, iMant2, iExp2, oMantR, oExpR);

	//generador de senales
	initial
		begin
			iMant1 = 15'h10;
			iExp1 = 5'h01;
			iMant2 = 15'h10;
			iExp2 = 5'h00;
			$display("Valores Iniciales \n");
			$display("iMant1=%h, iExp1=%h, iMant2=%h, iExp2=%h", iMant1, iExp1, iMant2, iExp2);
			$display("Resultado: ");
		end
/*
	initial
		begin
			#41 iMant1 = iMant1 + 15'h01;
			iExp1 = iExp1 + 5'h01;
			iMant2 = iMant2 + 15'h01;
			iExp2 = iExp2 + 5'h00;
		end
*/
	initial
		#100 $finish;

	initial
		begin
			$monitor($time, "   oMantR=%h, oExpR=%h", oMantR, oExpR);
			$dumpfile("float_adder_testbench.vcd");
			$dumpvars;

		end
endmodule

Sources/float_adder_testbench.vcd
$date
	Wed Dec 17 10:44:06 2014
$end
$version
	Icarus Verilog
$end
$timescale
	1s
$end
$scope module float_adder_testbench $end
$var wire 15 ! oMantR [14:0] $end
$var wire 5 " oExpR [4:0] $end
$var reg 1 # clcext $end
$var reg 1 $ clk $end
$var reg 5 % iExp1 [4:0] $end
$var reg 5 & iExp2 [4:0] $end
$var reg 15 ' iMant1 [14:0] $end
$var reg 15 ( iMant2 [14:0] $end
$scope module F1 $end
$var wire 1 # clcExt $end
$var wire 1 $ clkNorm $end
$var wire 5 ) iExp1 [4:0] $end
$var wire 5 * iExp2 [4:0] $end
$var wire 15 + iMant1 [14:0] $end
$var wire 15 , iMant2 [14:0] $end
$var wire 5 - oExpR [4:0] $end
$var wire 5 . q4 [4:0] $end
$var wire 16 / q3_dcp [15:0] $end
$var wire 16 0 q3 [15:0] $end
$var wire 15 1 oMantR [14:0] $end
$var wire 1 2 Mantisa_sign $end
$var wire 16 3 MantisaPre_cp [15:0] $end
$var reg 5 4 ExpPre [4:0] $end
$var reg 15 5 Mant3 [14:0] $end
$var reg 16 6 MantisaPre [15:0] $end
$scope module complementData51 $end
$var wire 16 7 a [15:0] $end
$var wire 1 2 sign $end
$var wire 16 8 b [15:0] $end
$upscope $end
$scope module descomp1 $end
$var wire 1 2 signAnt $end
$var wire 16 9 b [15:0] $end
$var wire 16 : a [15:0] $end
$upscope $end
$scope module renormalize $end
$var wire 1 # Clock $end
$var wire 1 $ clkNorm $end
$var wire 5 ; iExp [4:0] $end
$var wire 16 < iVect [15:0] $end
$var wire 16 = reMantReal0 [15:0] $end
$var wire 5 > reExpReal0 [4:0] $end
$var wire 16 ? oMant [15:0] $end
$var wire 5 @ oExp [4:0] $end
$var wire 16 A mantisaReal0 [15:0] $end
$var wire 5 B expReal0 [4:0] $end
$scope module muxExpoReal0 $end
$var wire 1 # a1 $end
$var wire 5 C sel1 [4:0] $end
$var wire 5 D sel0 [4:0] $end
$var reg 5 E q0 [4:0] $end
$upscope $end
$scope module muxMantReal0 $end
$var wire 1 # a1 $end
$var wire 16 F sel1 [15:0] $end
$var wire 16 G sel0 [15:0] $end
$var reg 16 H q0 [15:0] $end
$upscope $end
$scope module normReal0 $end
$var wire 1 $ clkNorm $end
$var wire 1 I enable $end
$var wire 5 J exp [4:0] $end
$var wire 16 K vect [15:0] $end
$var reg 16 L q1 [15:0] $end
$var reg 5 M q2 [4:0] $end
$var reg 16 N q3 [15:0] $end
$var reg 5 O q4 [4:0] $end
$upscope $end
$upscope $end
$upscope $end
$upscope $end
$enddefinitions $end
#0
$dumpvars
bx O
bx N
bx M
bx L
b11000 K
b1 J
0I
b11000 H
bx G
b11000 F
b1 E
bx D
b1 C
b1 B
b11000 A
bx @
bx ?
bx >
bx =
b11000 <
b1 ;
bx :
bx 9
b11000 8
b11000 7
b11000 6
b1000 5
b1 4
b11000 3
02
bx 1
bx 0
bx /
bx .
bx -
b10000 ,
b10000 +
b0 *
b1 )
b10000 (
b10000 '
b0 &
b1 %
0$
1#
bx "
bx !
$end
#1
1$
#2
0$
#3
1$
#4
0$
#5
1$
#6
0$
#7
1$
#8
0$
#9
1$
#10
0$
#11
1$
#12
0$
#13
1$
#14
0$
#15
1$
#16
0$
#17
1$
#18
0$
#19
1$
#20
0$
#21
1$
#22
0$
#23
1$
#24
0$
#25
1$
#26
0$
#27
1$
#28
0$
#29
1$
#30
0$
#31
1$
#32
0$
#33
1$
#34
0$
#35
1$
#36
0$
#37
1$
#38
0$
#39
1$
#40
b0 B
b0 E
b0 J
b110000 A
b110000 H
b110000 K
b0 >
b0 D
b0 M
b110000 =
b110000 G
b110000 L
1I
0$
0#
#41
1$
#42
b11111 B
b11111 E
b11111 J
b1100000 A
b1100000 H
b1100000 K
b11111 >
b11111 D
b11111 M
b1100000 =
b1100000 G
b1100000 L
0$
#43
1$
#44
b11110 B
b11110 E
b11110 J
b11000000 A
b11000000 H
b11000000 K
b11110 >
b11110 D
b11110 M
b11000000 =
b11000000 G
b11000000 L
0$
#45
1$
#46
b11101 B
b11101 E
b11101 J
b110000000 A
b110000000 H
b110000000 K
b11101 >
b11101 D
b11101 M
b110000000 =
b110000000 G
b110000000 L
0$
#47
1$
#48
b11100 B
b11100 E
b11100 J
b1100000000 A
b1100000000 H
b1100000000 K
b11100 >
b11100 D
b11100 M
b1100000000 =
b1100000000 G
b1100000000 L
0$
#49
1$
#50
b11011 B
b11011 E
b11011 J
b11000000000 A
b11000000000 H
b11000000000 K
b11011 >
b11011 D
b11011 M
b11000000000 =
b11000000000 G
b11000000000 L
0$
#51
1$
#52
b11010 B
b11010 E
b11010 J
b110000000000 A
b110000000000 H
b110000000000 K
b11010 >
b11010 D
b11010 M
b110000000000 =
b110000000000 G
b110000000000 L
0$
#53
1$
#54
b11001 B
b11001 E
b11001 J
b1100000000000 A
b1100000000000 H
b1100000000000 K
b11001 >
b11001 D
b11001 M
b1100000000000 =
b1100000000000 G
b1100000000000 L
0$
#55
1$
#56
b11000 B
b11000 E
b11000 J
b11000000000000 A
b11000000000000 H
b11000000000000 K
b11000 >
b11000 D
b11000 M
b11000000000000 =
b11000000000000 G
b11000000000000 L
0$
#57
1$
#58
b10111 B
b10111 E
b10111 J
b110000000000000 A
b110000000000000 H
b110000000000000 K
b10111 >
b10111 D
b10111 M
b110000000000000 =
b110000000000000 G
b110000000000000 L
0$
#59
1$
#60
b10110 B
b10110 E
b10110 J
b1100000000000000 A
b1100000000000000 H
b1100000000000000 K
b10110 >
b10110 D
b10110 M
b1100000000000000 =
b1100000000000000 G
b1100000000000000 L
0$
#61
1$
#62
b11000000000000 !
b11000000000000 1
b110000000000000 /
b110000000000000 9
b10111 "
b10111 -
b10111 .
b10111 @
b10111 O
b110000000000000 0
b110000000000000 :
b110000000000000 ?
b110000000000000 N
0$
#63
1$
#64
0$
#65
1$
#66
0$
#67
1$
#68
0$
#69
1$
#70
0$
#71
1$
#72
0$
#73
1$
#74
0$
#75
1$
#76
0$
#77
1$
#78
0$
#79
1$
#80
b1 B
b1 E
b1 J
b11000 A
b11000 H
b11000 K
0I
0$
1#
